vbimagetotext/__init__.py
vbimagetotext/__main__.py
vbimagetotext/agentic/__init__.py
vbimagetotext/agentic/__pycache__/__init__.cpython-312.pyc
vbimagetotext/agentic/__pycache__/cli.cpython-312.pyc
vbimagetotext/agentic/__pycache__/curriculum.cpython-312.pyc
vbimagetotext/agentic/__pycache__/db.cpython-312.pyc
vbimagetotext/agentic/__pycache__/runner.cpython-312.pyc
vbimagetotext/agentic/__pycache__/verify_utils.cpython-312.pyc
vbimagetotext/agentic/cli.py
vbimagetotext/agentic/commands/__init__.py
vbimagetotext/agentic/commands/__pycache__/__init__.cpython-312.pyc
vbimagetotext/agentic/commands/__pycache__/animations.cpython-312.pyc
vbimagetotext/agentic/commands/__pycache__/batches.cpython-312.pyc
vbimagetotext/agentic/commands/__pycache__/classify.cpython-312.pyc
vbimagetotext/agentic/commands/__pycache__/export.cpython-312.pyc
vbimagetotext/agentic/commands/__pycache__/extract.cpython-312.pyc
vbimagetotext/agentic/commands/__pycache__/ingest.cpython-312.pyc
vbimagetotext/agentic/commands/__pycache__/init_db.cpython-312.pyc
vbimagetotext/agentic/commands/__pycache__/jobs.cpython-312.pyc
vbimagetotext/agentic/commands/__pycache__/run.cpython-312.pyc
vbimagetotext/agentic/commands/__pycache__/tikz_export.cpython-312.pyc
vbimagetotext/agentic/commands/__pycache__/tikz_extract.cpython-312.pyc
vbimagetotext/agentic/commands/__pycache__/variants.cpython-312.pyc
vbimagetotext/agentic/commands/__pycache__/verify.cpython-312.pyc
vbimagetotext/agentic/commands/animations.py
vbimagetotext/agentic/commands/batches.py
vbimagetotext/agentic/commands/classify.py
vbimagetotext/agentic/commands/export.py
vbimagetotext/agentic/commands/extract.py
vbimagetotext/agentic/commands/ingest.py
vbimagetotext/agentic/commands/init_db.py
vbimagetotext/agentic/commands/jobs.py
vbimagetotext/agentic/commands/run.py
vbimagetotext/agentic/commands/tikz_export.py
vbimagetotext/agentic/commands/tikz_extract.py
vbimagetotext/agentic/commands/variants.py
vbimagetotext/agentic/commands/verify.py
vbimagetotext-0.1.42.dist-info/METADATA
vbimagetotext-0.1.42.dist-info/WHEEL
vbimagetotext-0.1.42.dist-info/entry_points.txt
vbimagetotext-0.1.42.dist-info/RECORD
