Metadata-Version: 2.3
Name: vbimagetotext
Version: 0.1.42
Summary: A cli tool to convert image to text using openai's GPT-Vision API and google's Gemini Vision API
Author: vaibhavblayer
Author-email: vaibhavblayer@gmail.com
Requires-Python: >=3.12,<4.0
Classifier: Programming Language :: Python :: 3
Classifier: Programming Language :: Python :: 3.12
Classifier: Programming Language :: Python :: 3.13
Requires-Dist: click (>=8.1.7,<9.0.0)
Requires-Dist: google-genai
Requires-Dist: google-generativeai (>=0.5.0,<0.6.0)
Requires-Dist: openai (>=1.102.0,<2.0.0)
Requires-Dist: pillow (>=10.3.0,<11.0.0)
Requires-Dist: pypdf (>=5.0.1,<6.0.0)
Requires-Dist: pyperclip (>=1.8.2,<2.0.0)
Requires-Dist: requests (>=2.31.0,<3.0.0)
Requires-Dist: rich (>=13.7.1,<14.0.0)
Requires-Dist: toml (>=0.10.2,<0.11.0)
